netlicensing/__init__.py
netlicensing/netlicensing.py
tests/__init__.py
tests/conftest.py
tests/test_common.py
tests/test_licensee.py
netlicensing_client-0.0.5.dist-info/LICENSE
netlicensing_client-0.0.5.dist-info/METADATA
netlicensing_client-0.0.5.dist-info/WHEEL
netlicensing_client-0.0.5.dist-info/top_level.txt
netlicensing_client-0.0.5.dist-info/RECORD
