Metadata-Version: 2.1
Name: netlicensing-client
Version: 0.0.5
Summary: Python wrapper for Labs64 NetLicensing RESTful API
Home-page: https://netlicensing.io
Author: Labs64 NetLicensing
Author-email: info@netlicensing.io
License: Apache-2.0
Project-URL: Getting Started, https://netlicensing.io/getting-started/
Project-URL: Documentation, https://netlicensing.io/wiki/restful-api
Project-URL: Source, https://github.com/Labs64/NetLicensingClient-python
Project-URL: Changelog, https://github.com/Labs64/NetLicensingClient-python/releases
Project-URL: Tracker, https://github.com/Labs64/NetLicensingClient-python/issues
Project-URL: CI, https://github.com/Labs64/NetLicensingClient-python/actions
Keywords: labs64 netlicensing licensing licensing-as-a-service license license-management software-license client restful restful-api python wrapper api client
Platform: any
Classifier: Development Status :: 1 - Planning
Classifier: Environment :: Other Environment
Classifier: Intended Audience :: Developers
Classifier: Intended Audience :: Information Technology
Classifier: License :: OSI Approved :: Apache Software License
Classifier: Natural Language :: English
Classifier: Operating System :: OS Independent
Classifier: Programming Language :: Python
Classifier: Programming Language :: Python :: 3
Classifier: Programming Language :: Python :: 3.6
Classifier: Programming Language :: Python :: 3.7
Classifier: Programming Language :: Python :: 3.8
Classifier: Topic :: Software Development :: Libraries :: Python Modules
Classifier: Topic :: System :: Software Distribution
Classifier: Topic :: Utilities
Requires-Python: >=3.6
Requires-Dist: requests
